MANIFEST.in
README.rst
setup.py
weewsgi/__init__.py
weewsgi/wee.py
weewsgi.egg-info/PKG-INFO
weewsgi.egg-info/SOURCES.txt
weewsgi.egg-info/dependency_links.txt
weewsgi.egg-info/top_level.txt
weewsgi/test/__init__.py
weewsgi/test/test_wee.py